easyyaml/__init__.py
easyyaml/test.yaml
easyyaml-0.0.4.1.dist-info/METADATA
easyyaml-0.0.4.1.dist-info/RECORD
easyyaml-0.0.4.1.dist-info/WHEEL
easyyaml-0.0.4.1.dist-info/top_level.txt
