Metadata-Version: 2.1
Name: easyyaml
Version: 0.0.4.1
Summary: Easy yaml parser and editer
Home-page: https://github.com/ZQPei/easyyaml
Author: ZQPei
Author-email: dfzspzq@163.com
License: MIT
Platform: all
Requires-Dist: pyyaml
